cattrs_extras/__init__.py
cattrs_extras/converter.py
cattrs_extras/py.typed
cattrs_extras/tortoise/__init__.py
cattrs_extras/tortoise/converter.py
cattrs_extras/tortoise/fields.py
cattrs_extras/tortoise/model.py
cattrs_extras-0.2.0.dist-info/LICENSE
cattrs_extras-0.2.0.dist-info/WHEEL
cattrs_extras-0.2.0.dist-info/METADATA
cattrs_extras-0.2.0.dist-info/RECORD
