Metadata-Version: 2.1
Name: cattrs-extras
Version: 0.2.0
Summary: Advanced converters for cattrs
Home-page: https://github.com/droserasprout/cattrs-extras
Keywords: tortoise,cattrs,attrs,serialization,dataclass
Author: Lev Gorodetskiy
Author-email: github@droserasprout.space
Requires-Python: >=3.8,<4.0
Classifier: Development Status :: 4 - Beta
Classifier: License :: OSI Approved :: MIT License
Classifier: Programming Language :: Python :: 3
Classifier: Programming Language :: Python :: 3.10
Classifier: Programming Language :: Python :: 3.8
Classifier: Programming Language :: Python :: 3.9
Classifier: Topic :: Software Development
Classifier: Typing :: Typed
Provides-Extra: tortoise
Requires-Dist: cattrs (>=1.9.0,<2.0.0)
Requires-Dist: dateutils (>=0.6.12,<0.7.0)
Requires-Dist: pytimeparse (>=1.1.8,<2.0.0)
Requires-Dist: tortoise-orm (>=0.18.0,<0.19.0); extra == "tortoise"
Requires-Dist: typing-extensions (>=4.0.1,<5.0.0)
Requires-Dist: typing-inspect (>=0.7.1,<0.8.0)
Project-URL: Repository, https://github.com/droserasprout/cattrs-extras
